<stg><name>cnn_lenet_Pipeline_col_loop2_kernelRow_Loop2_kernelCol_loop2</name>


<trans_list>

<trans id="119" from="1" to="2">
<condition id="-1">
<or_exp><and_exp></and_exp></or_exp>
</condition>
</trans>

<trans id="108" from="2" to="3">
<condition id="-1">
<or_exp><and_exp></and_exp></or_exp>
</condition>
</trans>

<trans id="109" from="3" to="4">
<condition id="-1">
<or_exp><and_exp></and_exp></or_exp>
</condition>
</trans>

<trans id="110" from="4" to="5">
<condition id="-1">
<or_exp><and_exp></and_exp></or_exp>
</condition>
</trans>

<trans id="111" from="5" to="6">
<condition id="-1">
<or_exp><and_exp></and_exp></or_exp>
</condition>
</trans>

<trans id="112" from="6" to="7">
<condition id="-1">
<or_exp><and_exp></and_exp></or_exp>
</condition>
</trans>

<trans id="113" from="7" to="8">
<condition id="-1">
<or_exp><and_exp></and_exp></or_exp>
</condition>
</trans>

<trans id="114" from="8" to="9">
<condition id="-1">
<or_exp><and_exp></and_exp></or_exp>
</condition>
</trans>

<trans id="115" from="9" to="10">
<condition id="-1">
<or_exp><and_exp></and_exp></or_exp>
</condition>
</trans>

<trans id="116" from="10" to="11">
<condition id="-1">
<or_exp><and_exp></and_exp></or_exp>
</condition>
</trans>
</trans_list>



<state_list>

<state id="1" st_id="2">

<operation id="14" st_id="1" stage="1" lat="1">
<core>NULL</core>
<MemPortIdVec></MemPortIdVec>
<condition id="-1">
<or_exp><and_exp></and_exp></or_exp>
</condition>

<Node id="6" bw="32" op_0_bw="32">
<![CDATA[
newFuncRoot:0 %somme_1 = alloca i32 1

]]></Node>
<StgValue><ssdm name="somme_1"/></StgValue>
</operation>

<operation id="15" st_id="1" stage="1" lat="1">
<core>NULL</core>
<MemPortIdVec></MemPortIdVec>
<condition id="-1">
<or_exp><and_exp></and_exp></or_exp>
</condition>

<Node id="7" bw="3" op_0_bw="32">
<![CDATA[
newFuncRoot:1 %m = alloca i32 1

]]></Node>
<StgValue><ssdm name="m"/></StgValue>
</operation>

<operation id="16" st_id="1" stage="1" lat="1">
<core>NULL</core>
<MemPortIdVec></MemPortIdVec>
<condition id="-1">
<or_exp><and_exp></and_exp></or_exp>
</condition>

<Node id="8" bw="3" op_0_bw="32">
<![CDATA[
newFuncRoot:2 %k = alloca i32 1

]]></Node>
<StgValue><ssdm name="k"/></StgValue>
</operation>

<operation id="17" st_id="1" stage="1" lat="1">
<core>NULL</core>
<MemPortIdVec></MemPortIdVec>
<condition id="-1">
<or_exp><and_exp></and_exp></or_exp>
</condition>

<Node id="9" bw="6" op_0_bw="32">
<![CDATA[
newFuncRoot:3 %indvar_flatten51 = alloca i32 1

]]></Node>
<StgValue><ssdm name="indvar_flatten51"/></StgValue>
</operation>

<operation id="18" st_id="1" stage="1" lat="1">
<core>NULL</core>
<MemPortIdVec></MemPortIdVec>
<condition id="-1">
<or_exp><and_exp></and_exp></or_exp>
</condition>

<Node id="10" bw="6" op_0_bw="32">
<![CDATA[
newFuncRoot:4 %j = alloca i32 1

]]></Node>
<StgValue><ssdm name="j"/></StgValue>
</operation>

<operation id="19" st_id="1" stage="1" lat="1">
<core>NULL</core>
<MemPortIdVec></MemPortIdVec>
<condition id="-1">
<or_exp><and_exp></and_exp></or_exp>
</condition>

<Node id="11" bw="11" op_0_bw="32">
<![CDATA[
newFuncRoot:5 %indvar_flatten66 = alloca i32 1

]]></Node>
<StgValue><ssdm name="indvar_flatten66"/></StgValue>
</operation>

<operation id="20" st_id="1" stage="1" lat="1">
<core>NULL</core>
<MemPortIdVec></MemPortIdVec>
<condition id="-1">
<or_exp><and_exp></and_exp></or_exp>
</condition>

<Node id="12" bw="62" op_0_bw="62" op_1_bw="62">
<![CDATA[
newFuncRoot:6 %sext_ln75_read = read i62 @_ssdm_op_Read.ap_auto.i62, i62 %sext_ln75

]]></Node>
<StgValue><ssdm name="sext_ln75_read"/></StgValue>
</operation>

<operation id="21" st_id="1" stage="1" lat="1">
<core>NULL</core>
<MemPortIdVec></MemPortIdVec>
<condition id="-1">
<or_exp><and_exp></and_exp></or_exp>
</condition>

<Node id="13" bw="32" op_0_bw="32" op_1_bw="32">
<![CDATA[
newFuncRoot:7 %somme_read = read i32 @_ssdm_op_Read.ap_auto.float, i32 %somme

]]></Node>
<StgValue><ssdm name="somme_read"/></StgValue>
</operation>

<operation id="22" st_id="1" stage="1" lat="1">
<core>NULL</core>
<MemPortIdVec></MemPortIdVec>
<condition id="-1">
<or_exp><and_exp></and_exp></or_exp>
</condition>

<Node id="14" bw="64" op_0_bw="62">
<![CDATA[
newFuncRoot:8 %sext_ln75_cast = sext i62 %sext_ln75_read

]]></Node>
<StgValue><ssdm name="sext_ln75_cast"/></StgValue>
</operation>

<operation id="23" st_id="1" stage="1" lat="1">
<core>NULL</core>
<MemPortIdVec></MemPortIdVec>
<condition id="-1">
<or_exp><and_exp></and_exp></or_exp>
</condition>

<Node id="15" bw="0" op_0_bw="0" op_1_bw="32" op_2_bw="0" op_3_bw="32" op_4_bw="32" op_5_bw="0" op_6_bw="32" op_7_bw="32" op_8_bw="0" op_9_bw="0" op_10_bw="0" op_11_bw="32" op_12_bw="32" op_13_bw="32" op_14_bw="32" op_15_bw="0" op_16_bw="0" op_17_bw="32" op_18_bw="32">
<![CDATA[
newFuncRoot:9 %specinterface_ln0 = specinterface void @_ssdm_op_SpecInterface, i32 %Layer_Weights, void @empty, i32 0, i32 0, void @empty_0, i32 0, i32 156, void @empty_3, void @empty_2, void @empty_0, i32 16, i32 16, i32 16, i32 16, void @empty_0, void @empty_0, i32 4294967295, i32 0

]]></Node>
<StgValue><ssdm name="specinterface_ln0"/></StgValue>
</operation>

<operation id="24" st_id="1" stage="1" lat="1">
<core>NULL</core>
<MemPortIdVec></MemPortIdVec>
<condition id="-1">
<or_exp><and_exp></and_exp></or_exp>
</condition>

<Node id="16" bw="0" op_0_bw="11" op_1_bw="11">
<![CDATA[
newFuncRoot:10 %store_ln0 = store i11 0, i11 %indvar_flatten66

]]></Node>
<StgValue><ssdm name="store_ln0"/></StgValue>
</operation>

<operation id="25" st_id="1" stage="1" lat="1">
<core>NULL</core>
<MemPortIdVec></MemPortIdVec>
<condition id="-1">
<or_exp><and_exp></and_exp></or_exp>
</condition>

<Node id="17" bw="0" op_0_bw="6" op_1_bw="6">
<![CDATA[
newFuncRoot:11 %store_ln30 = store i6 0, i6 %j

]]></Node>
<StgValue><ssdm name="store_ln30"/></StgValue>
</operation>

<operation id="26" st_id="1" stage="1" lat="1">
<core>NULL</core>
<MemPortIdVec></MemPortIdVec>
<condition id="-1">
<or_exp><and_exp></and_exp></or_exp>
</condition>

<Node id="18" bw="0" op_0_bw="6" op_1_bw="6">
<![CDATA[
newFuncRoot:12 %store_ln0 = store i6 0, i6 %indvar_flatten51

]]></Node>
<StgValue><ssdm name="store_ln0"/></StgValue>
</operation>

<operation id="27" st_id="1" stage="1" lat="1">
<core>NULL</core>
<MemPortIdVec></MemPortIdVec>
<condition id="-1">
<or_exp><and_exp></and_exp></or_exp>
</condition>

<Node id="19" bw="0" op_0_bw="3" op_1_bw="3">
<![CDATA[
newFuncRoot:13 %store_ln30 = store i3 0, i3 %k

]]></Node>
<StgValue><ssdm name="store_ln30"/></StgValue>
</operation>

<operation id="28" st_id="1" stage="1" lat="1">
<core>NULL</core>
<MemPortIdVec></MemPortIdVec>
<condition id="-1">
<or_exp><and_exp></and_exp></or_exp>
</condition>

<Node id="20" bw="0" op_0_bw="3" op_1_bw="3">
<![CDATA[
newFuncRoot:14 %store_ln30 = store i3 0, i3 %m

]]></Node>
<StgValue><ssdm name="store_ln30"/></StgValue>
</operation>

<operation id="29" st_id="1" stage="1" lat="1">
<core>NULL</core>
<MemPortIdVec></MemPortIdVec>
<condition id="-1">
<or_exp><and_exp></and_exp></or_exp>
</condition>

<Node id="21" bw="0" op_0_bw="32" op_1_bw="32">
<![CDATA[
newFuncRoot:15 %store_ln29 = store i32 %somme_read, i32 %somme_1

]]></Node>
<StgValue><ssdm name="store_ln29"/></StgValue>
</operation>

<operation id="30" st_id="1" stage="1" lat="1">
<core>NULL</core>
<MemPortIdVec></MemPortIdVec>
<condition id="-1">
<or_exp><and_exp></and_exp></or_exp>
</condition>

<Node id="22" bw="0" op_0_bw="0">
<![CDATA[
newFuncRoot:16 %br_ln0 = br void %for.inc238

]]></Node>
<StgValue><ssdm name="br_ln0"/></StgValue>
</operation>

<operation id="31" st_id="1" stage="1" lat="1">
<core>NULL</core>
<MemPortIdVec></MemPortIdVec>
<condition id="-1">
<or_exp><and_exp></and_exp></or_exp>
</condition>

<Node id="24" bw="11" op_0_bw="11" op_1_bw="0">
<![CDATA[
for.inc238:0 %indvar_flatten66_load = load i11 %indvar_flatten66

]]></Node>
<StgValue><ssdm name="indvar_flatten66_load"/></StgValue>
</operation>

<operation id="32" st_id="1" stage="1" lat="1">
<core>NULL</core>
<MemPortIdVec></MemPortIdVec>
<condition id="-1">
<or_exp><and_exp></and_exp></or_exp>
</condition>

<Node id="25" bw="0" op_0_bw="0" op_1_bw="32">
<![CDATA[
for.inc238:1 %specbitsmap_ln0 = specbitsmap void @_ssdm_op_SpecBitsMap, i32 %Layer_Weights

]]></Node>
<StgValue><ssdm name="specbitsmap_ln0"/></StgValue>
</operation>

<operation id="33" st_id="1" stage="1" lat="1">
<core>Cmp</core>
<MemPortIdVec></MemPortIdVec>
<condition id="-1">
<or_exp><and_exp></and_exp></or_exp>
</condition>

<Node id="26" bw="1" op_0_bw="11" op_1_bw="11">
<![CDATA[
for.inc238:2 %icmp_ln75 = icmp_eq  i11 %indvar_flatten66_load, i11 1250

]]></Node>
<StgValue><ssdm name="icmp_ln75"/></StgValue>
</operation>

<operation id="34" st_id="1" stage="1" lat="1">
<core>Adder</core>
<MemPortIdVec></MemPortIdVec>
<condition id="-1">
<or_exp><and_exp></and_exp></or_exp>
</condition>

<Node id="27" bw="11" op_0_bw="11" op_1_bw="11">
<![CDATA[
for.inc238:3 %add_ln75 = add i11 %indvar_flatten66_load, i11 1

]]></Node>
<StgValue><ssdm name="add_ln75"/></StgValue>
</operation>

<operation id="35" st_id="1" stage="1" lat="1">
<core>NULL</core>
<MemPortIdVec></MemPortIdVec>
<condition id="-1">
<or_exp><and_exp></and_exp></or_exp>
</condition>

<Node id="28" bw="0" op_0_bw="1" op_1_bw="0" op_2_bw="0">
<![CDATA[
for.inc238:4 %br_ln75 = br i1 %icmp_ln75, void %for.inc244, void %for.inc250.exitStub

]]></Node>
<StgValue><ssdm name="br_ln75"/></StgValue>
</operation>

<operation id="36" st_id="1" stage="1" lat="1">
<core>NULL</core>
<MemPortIdVec></MemPortIdVec>
<condition id="-1">
<or_exp><and_exp><literal name="icmp_ln75" val="0"/>
</and_exp></or_exp>
</condition>

<Node id="33" bw="6" op_0_bw="6" op_1_bw="0">
<![CDATA[
for.inc244:3 %indvar_flatten51_load = load i6 %indvar_flatten51

]]></Node>
<StgValue><ssdm name="indvar_flatten51_load"/></StgValue>
</operation>

<operation id="37" st_id="1" stage="1" lat="1">
<core>NULL</core>
<MemPortIdVec></MemPortIdVec>
<condition id="-1">
<or_exp><and_exp><literal name="icmp_ln75" val="0"/>
</and_exp></or_exp>
</condition>

<Node id="34" bw="6" op_0_bw="6" op_1_bw="0">
<![CDATA[
for.inc244:4 %j_load = load i6 %j

]]></Node>
<StgValue><ssdm name="j_load"/></StgValue>
</operation>

<operation id="38" st_id="1" stage="1" lat="1">
<core>Cmp</core>
<MemPortIdVec></MemPortIdVec>
<condition id="-1">
<or_exp><and_exp><literal name="icmp_ln75" val="0"/>
</and_exp></or_exp>
</condition>

<Node id="38" bw="1" op_0_bw="6" op_1_bw="6">
<![CDATA[
for.inc244:8 %icmp_ln76 = icmp_eq  i6 %indvar_flatten51_load, i6 25

]]></Node>
<StgValue><ssdm name="icmp_ln76"/></StgValue>
</operation>

<operation id="39" st_id="1" stage="1" lat="1">
<core>Adder</core>
<MemPortIdVec></MemPortIdVec>
<condition id="-1">
<or_exp><and_exp><literal name="icmp_ln75" val="0"/>
</and_exp></or_exp>
</condition>

<Node id="43" bw="6" op_0_bw="6" op_1_bw="6">
<![CDATA[
for.inc244:13 %add_ln75_1 = add i6 %j_load, i6 1

]]></Node>
<StgValue><ssdm name="add_ln75_1"/></StgValue>
</operation>

<operation id="40" st_id="1" stage="1" lat="1">
<core>Sel</core>
<MemPortIdVec></MemPortIdVec>
<condition id="-1">
<or_exp><and_exp><literal name="icmp_ln75" val="0"/>
</and_exp></or_exp>
</condition>

<Node id="44" bw="6" op_0_bw="1" op_1_bw="6" op_2_bw="6">
<![CDATA[
for.inc244:14 %select_ln75 = select i1 %icmp_ln76, i6 %add_ln75_1, i6 %j_load

]]></Node>
<StgValue><ssdm name="select_ln75"/></StgValue>
</operation>

<operation id="41" st_id="1" stage="1" lat="1">
<core>NULL</core>
<MemPortIdVec></MemPortIdVec>
<condition id="-1">
<or_exp><and_exp><literal name="icmp_ln75" val="0"/>
</and_exp></or_exp>
</condition>

<Node id="49" bw="11" op_0_bw="6">
<![CDATA[
for.inc244:19 %zext_ln75 = zext i6 %select_ln75

]]></Node>
<StgValue><ssdm name="zext_ln75"/></StgValue>
</operation>

<operation id="42" st_id="1" stage="3" lat="3">
<core>DSP48</core>
<MemPortIdVec></MemPortIdVec>
<condition id="-1">
<or_exp><and_exp><literal name="icmp_ln75" val="0"/>
</and_exp></or_exp>
</condition>

<Node id="50" bw="11" op_0_bw="11" op_1_bw="11">
<![CDATA[
for.inc244:20 %empty = mul i11 %zext_ln75, i11 25

]]></Node>
<StgValue><ssdm name="empty"/></StgValue>
</operation>

<operation id="43" st_id="1" stage="1" lat="1">
<core>Adder</core>
<MemPortIdVec></MemPortIdVec>
<condition id="-1">
<or_exp><and_exp><literal name="icmp_ln75" val="0"/>
</and_exp></or_exp>
</condition>

<Node id="67" bw="6" op_0_bw="6" op_1_bw="6">
<![CDATA[
for.inc244:37 %add_ln76_1 = add i6 %indvar_flatten51_load, i6 1

]]></Node>
<StgValue><ssdm name="add_ln76_1"/></StgValue>
</operation>

<operation id="44" st_id="1" stage="1" lat="1">
<core>Sel</core>
<MemPortIdVec></MemPortIdVec>
<condition id="-1">
<or_exp><and_exp><literal name="icmp_ln75" val="0"/>
</and_exp></or_exp>
</condition>

<Node id="68" bw="6" op_0_bw="1" op_1_bw="6" op_2_bw="6">
<![CDATA[
for.inc244:38 %select_ln76_1 = select i1 %icmp_ln76, i6 1, i6 %add_ln76_1

]]></Node>
<StgValue><ssdm name="select_ln76_1"/></StgValue>
</operation>

<operation id="45" st_id="1" stage="1" lat="1">
<core>NULL</core>
<MemPortIdVec></MemPortIdVec>
<condition id="-1">
<or_exp><and_exp><literal name="icmp_ln75" val="0"/>
</and_exp></or_exp>
</condition>

<Node id="69" bw="0" op_0_bw="11" op_1_bw="11" op_2_bw="0" op_3_bw="0">
<![CDATA[
for.inc244:39 %store_ln75 = store i11 %add_ln75, i11 %indvar_flatten66

]]></Node>
<StgValue><ssdm name="store_ln75"/></StgValue>
</operation>

<operation id="46" st_id="1" stage="1" lat="1">
<core>NULL</core>
<MemPortIdVec></MemPortIdVec>
<condition id="-1">
<or_exp><and_exp><literal name="icmp_ln75" val="0"/>
</and_exp></or_exp>
</condition>

<Node id="70" bw="0" op_0_bw="6" op_1_bw="6" op_2_bw="0" op_3_bw="0">
<![CDATA[
for.inc244:40 %store_ln30 = store i6 %select_ln75, i6 %j

]]></Node>
<StgValue><ssdm name="store_ln30"/></StgValue>
</operation>

<operation id="47" st_id="1" stage="1" lat="1">
<core>NULL</core>
<MemPortIdVec></MemPortIdVec>
<condition id="-1">
<or_exp><and_exp><literal name="icmp_ln75" val="0"/>
</and_exp></or_exp>
</condition>

<Node id="71" bw="0" op_0_bw="6" op_1_bw="6" op_2_bw="0" op_3_bw="0">
<![CDATA[
for.inc244:41 %store_ln76 = store i6 %select_ln76_1, i6 %indvar_flatten51

]]></Node>
<StgValue><ssdm name="store_ln76"/></StgValue>
</operation>
</state>

<state id="2" st_id="3">

<operation id="48" st_id="2" stage="2" lat="3">
<core>DSP48</core>
<MemPortIdVec></MemPortIdVec>
<condition id="-1">
<or_exp><and_exp><literal name="icmp_ln75" val="0"/>
</and_exp></or_exp>
</condition>

<Node id="50" bw="11" op_0_bw="11" op_1_bw="11">
<![CDATA[
for.inc244:20 %empty = mul i11 %zext_ln75, i11 25

]]></Node>
<StgValue><ssdm name="empty"/></StgValue>
</operation>
</state>

<state id="3" st_id="4">

<operation id="49" st_id="3" stage="1" lat="1">
<core>NULL</core>
<MemPortIdVec></MemPortIdVec>
<condition id="-1">
<or_exp><and_exp><literal name="icmp_ln75" val="0"/>
</and_exp></or_exp>
</condition>

<Node id="31" bw="3" op_0_bw="3" op_1_bw="0">
<![CDATA[
for.inc244:1 %m_load = load i3 %m

]]></Node>
<StgValue><ssdm name="m_load"/></StgValue>
</operation>

<operation id="50" st_id="3" stage="1" lat="1">
<core>LogicGate</core>
<MemPortIdVec></MemPortIdVec>
<condition id="-1">
<or_exp><and_exp><literal name="icmp_ln75" val="0"/>
</and_exp></or_exp>
</condition>

<Node id="40" bw="1" op_0_bw="1" op_1_bw="1">
<![CDATA[
for.inc244:10 %xor_ln29 = xor i1 %icmp_ln76, i1 1

]]></Node>
<StgValue><ssdm name="xor_ln29"/></StgValue>
</operation>

<operation id="51" st_id="3" stage="1" lat="1">
<core>Cmp</core>
<MemPortIdVec></MemPortIdVec>
<condition id="-1">
<or_exp><and_exp><literal name="icmp_ln75" val="0"/>
</and_exp></or_exp>
</condition>

<Node id="41" bw="1" op_0_bw="3" op_1_bw="3">
<![CDATA[
for.inc244:11 %icmp_ln77 = icmp_eq  i3 %m_load, i3 5

]]></Node>
<StgValue><ssdm name="icmp_ln77"/></StgValue>
</operation>

<operation id="52" st_id="3" stage="1" lat="1">
<core>LogicGate</core>
<MemPortIdVec></MemPortIdVec>
<condition id="-1">
<or_exp><and_exp><literal name="icmp_ln75" val="0"/>
</and_exp></or_exp>
</condition>

<Node id="42" bw="1" op_0_bw="1" op_1_bw="1">
<![CDATA[
for.inc244:12 %and_ln29 = and i1 %icmp_ln77, i1 %xor_ln29

]]></Node>
<StgValue><ssdm name="and_ln29"/></StgValue>
</operation>

<operation id="53" st_id="3" stage="1" lat="1">
<core>LogicGate</core>
<MemPortIdVec></MemPortIdVec>
<condition id="-1">
<or_exp><and_exp><literal name="icmp_ln75" val="0"/>
</and_exp></or_exp>
</condition>

<Node id="46" bw="1" op_0_bw="1" op_1_bw="1">
<![CDATA[
for.inc244:16 %or_ln29 = or i1 %and_ln29, i1 %icmp_ln76

]]></Node>
<StgValue><ssdm name="or_ln29"/></StgValue>
</operation>

<operation id="54" st_id="3" stage="1" lat="1">
<core>Sel</core>
<MemPortIdVec></MemPortIdVec>
<condition id="-1">
<or_exp><and_exp><literal name="icmp_ln75" val="0"/>
</and_exp></or_exp>
</condition>

<Node id="47" bw="3" op_0_bw="1" op_1_bw="3" op_2_bw="3">
<![CDATA[
for.inc244:17 %select_ln29_1 = select i1 %or_ln29, i3 0, i3 %m_load

]]></Node>
<StgValue><ssdm name="select_ln29_1"/></StgValue>
</operation>

<operation id="55" st_id="3" stage="1" lat="3">
<core>DSP48</core>
<MemPortIdVec></MemPortIdVec>
<condition id="-1">
<or_exp><and_exp><literal name="icmp_ln75" val="0"/>
</and_exp></or_exp>
</condition>

<Node id="50" bw="11" op_0_bw="11" op_1_bw="11">
<![CDATA[
for.inc244:20 %empty = mul i11 %zext_ln75, i11 25

]]></Node>
<StgValue><ssdm name="empty"/></StgValue>
</operation>

<operation id="56" st_id="3" stage="1" lat="1">
<core>NULL</core>
<MemPortIdVec></MemPortIdVec>
<condition id="-1">
<or_exp><and_exp><literal name="icmp_ln75" val="0"/>
</and_exp></or_exp>
</condition>

<Node id="53" bw="11" op_0_bw="3">
<![CDATA[
for.inc244:23 %zext_ln77 = zext i3 %select_ln29_1

]]></Node>
<StgValue><ssdm name="zext_ln77"/></StgValue>
</operation>

<operation id="57" st_id="3" stage="2" lat="2">
<core>DSP48</core>
<MemPortIdVec></MemPortIdVec>
<condition id="-1">
<or_exp><and_exp><literal name="icmp_ln75" val="0"/>
</and_exp></or_exp>
</condition>

<Node id="59" bw="11" op_0_bw="11" op_1_bw="11">
<![CDATA[
for.inc244:29 %add_ln79_2 = add i11 %empty, i11 %zext_ln77

]]></Node>
<StgValue><ssdm name="add_ln79_2"/></StgValue>
</operation>

<operation id="58" st_id="3" stage="1" lat="1">
<core>Adder</core>
<MemPortIdVec></MemPortIdVec>
<condition id="-1">
<or_exp><and_exp><literal name="icmp_ln75" val="0"/>
</and_exp></or_exp>
</condition>

<Node id="66" bw="3" op_0_bw="3" op_1_bw="3">
<![CDATA[
for.inc244:36 %add_ln77 = add i3 %select_ln29_1, i3 1

]]></Node>
<StgValue><ssdm name="add_ln77"/></StgValue>
</operation>

<operation id="59" st_id="3" stage="1" lat="1">
<core>NULL</core>
<MemPortIdVec></MemPortIdVec>
<condition id="-1">
<or_exp><and_exp><literal name="icmp_ln75" val="0"/>
</and_exp></or_exp>
</condition>

<Node id="73" bw="0" op_0_bw="3" op_1_bw="3" op_2_bw="0" op_3_bw="0">
<![CDATA[
for.inc244:43 %store_ln30 = store i3 %add_ln77, i3 %m

]]></Node>
<StgValue><ssdm name="store_ln30"/></StgValue>
</operation>
</state>

<state id="4" st_id="5">

<operation id="60" st_id="4" stage="1" lat="1">
<core>NULL</core>
<MemPortIdVec></MemPortIdVec>
<condition id="-1">
<or_exp><and_exp><literal name="icmp_ln76" val="0"/>
</and_exp></or_exp>
</condition>

<Node id="32" bw="3" op_0_bw="3" op_1_bw="0">
<![CDATA[
for.inc244:2 %k_load = load i3 %k

]]></Node>
<StgValue><ssdm name="k_load"/></StgValue>
</operation>

<operation id="61" st_id="4" stage="1" lat="1">
<core>Sel</core>
<MemPortIdVec></MemPortIdVec>
<condition id="-1">
<or_exp><and_exp></and_exp></or_exp>
</condition>

<Node id="39" bw="3" op_0_bw="1" op_1_bw="3" op_2_bw="3">
<![CDATA[
for.inc244:9 %select_ln29 = select i1 %icmp_ln76, i3 0, i3 %k_load

]]></Node>
<StgValue><ssdm name="select_ln29"/></StgValue>
</operation>

<operation id="62" st_id="4" stage="1" lat="1">
<core>Adder</core>
<MemPortIdVec></MemPortIdVec>
<condition id="-1">
<or_exp><and_exp><literal name="and_ln29" val="1"/>
</and_exp></or_exp>
</condition>

<Node id="45" bw="3" op_0_bw="3" op_1_bw="3">
<![CDATA[
for.inc244:15 %add_ln76 = add i3 %select_ln29, i3 1

]]></Node>
<StgValue><ssdm name="add_ln76"/></StgValue>
</operation>

<operation id="63" st_id="4" stage="1" lat="1">
<core>Sel</core>
<MemPortIdVec></MemPortIdVec>
<condition id="-1">
<or_exp><and_exp></and_exp></or_exp>
</condition>

<Node id="48" bw="3" op_0_bw="1" op_1_bw="3" op_2_bw="3">
<![CDATA[
for.inc244:18 %select_ln76 = select i1 %and_ln29, i3 %add_ln76, i3 %select_ln29

]]></Node>
<StgValue><ssdm name="select_ln76"/></StgValue>
</operation>

<operation id="64" st_id="4" stage="1" lat="1">
<core>NULL</core>
<MemPortIdVec></MemPortIdVec>
<condition id="-1">
<or_exp><and_exp></and_exp></or_exp>
</condition>

<Node id="51" bw="5" op_0_bw="3">
<![CDATA[
for.inc244:21 %zext_ln76 = zext i3 %select_ln76

]]></Node>
<StgValue><ssdm name="zext_ln76"/></StgValue>
</operation>

<operation id="65" st_id="4" stage="1" lat="1">
<core>NULL</core>
<MemPortIdVec></MemPortIdVec>
<condition id="-1">
<or_exp><and_exp></and_exp></or_exp>
</condition>

<Node id="52" bw="5" op_0_bw="5" op_1_bw="3" op_2_bw="2">
<![CDATA[
for.inc244:22 %p_shl1 = bitconcatenate i5 @_ssdm_op_BitConcatenate.i5.i3.i2, i3 %select_ln76, i2 0

]]></Node>
<StgValue><ssdm name="p_shl1"/></StgValue>
</operation>

<operation id="66" st_id="4" stage="1" lat="1">
<core>Adder</core>
<MemPortIdVec></MemPortIdVec>
<condition id="-1">
<or_exp><and_exp></and_exp></or_exp>
</condition>

<Node id="57" bw="5" op_0_bw="5" op_1_bw="5">
<![CDATA[
for.inc244:27 %add_ln79 = add i5 %p_shl1, i5 %zext_ln76

]]></Node>
<StgValue><ssdm name="add_ln79"/></StgValue>
</operation>

<operation id="67" st_id="4" stage="1" lat="1">
<core>NULL</core>
<MemPortIdVec></MemPortIdVec>
<condition id="-1">
<or_exp><and_exp></and_exp></or_exp>
</condition>

<Node id="58" bw="11" op_0_bw="5">
<![CDATA[
for.inc244:28 %zext_ln79 = zext i5 %add_ln79

]]></Node>
<StgValue><ssdm name="zext_ln79"/></StgValue>
</operation>

<operation id="68" st_id="4" stage="1" lat="2">
<core>DSP48</core>
<MemPortIdVec></MemPortIdVec>
<condition id="-1">
<or_exp><and_exp></and_exp></or_exp>
</condition>

<Node id="59" bw="11" op_0_bw="11" op_1_bw="11">
<![CDATA[
for.inc244:29 %add_ln79_2 = add i11 %empty, i11 %zext_ln77

]]></Node>
<StgValue><ssdm name="add_ln79_2"/></StgValue>
</operation>

<operation id="69" st_id="4" stage="1" lat="1">
<core>Adder</core>
<MemPortIdVec></MemPortIdVec>
<condition id="-1">
<or_exp><and_exp></and_exp></or_exp>
</condition>

<Node id="60" bw="11" op_0_bw="11" op_1_bw="11">
<![CDATA[
for.inc244:30 %add_ln79_1 = add i11 %add_ln79_2, i11 %zext_ln79

]]></Node>
<StgValue><ssdm name="add_ln79_1"/></StgValue>
</operation>

<operation id="70" st_id="4" stage="1" lat="1">
<core>NULL</core>
<MemPortIdVec></MemPortIdVec>
<condition id="-1">
<or_exp><and_exp></and_exp></or_exp>
</condition>

<Node id="61" bw="64" op_0_bw="11">
<![CDATA[
for.inc244:31 %zext_ln79_1 = zext i11 %add_ln79_1

]]></Node>
<StgValue><ssdm name="zext_ln79_1"/></StgValue>
</operation>

<operation id="71" st_id="4" stage="1" lat="1">
<core>NULL</core>
<MemPortIdVec></MemPortIdVec>
<condition id="-1">
<or_exp><and_exp></and_exp></or_exp>
</condition>

<Node id="62" bw="11" op_0_bw="32" op_1_bw="64" op_2_bw="64">
<![CDATA[
for.inc244:32 %Layer3_Neurons_CPU_addr = getelementptr i32 %Layer3_Neurons_CPU, i64 0, i64 %zext_ln79_1

]]></Node>
<StgValue><ssdm name="Layer3_Neurons_CPU_addr"/></StgValue>
</operation>

<operation id="72" st_id="4" stage="2" lat="2">
<core>RAM</core>
<MemPortIdVec></MemPortIdVec>
<condition id="-1">
<or_exp><and_exp></and_exp></or_exp>
</condition>

<Node id="63" bw="32" op_0_bw="11">
<![CDATA[
for.inc244:33 %Layer3_Neurons_CPU_load = load i11 %Layer3_Neurons_CPU_addr

]]></Node>
<StgValue><ssdm name="Layer3_Neurons_CPU_load"/></StgValue>
</operation>

<operation id="73" st_id="4" stage="1" lat="1">
<core>NULL</core>
<MemPortIdVec></MemPortIdVec>
<condition id="-1">
<or_exp><and_exp></and_exp></or_exp>
</condition>

<Node id="72" bw="0" op_0_bw="3" op_1_bw="3" op_2_bw="0" op_3_bw="0">
<![CDATA[
for.inc244:42 %store_ln30 = store i3 %select_ln76, i3 %k

]]></Node>
<StgValue><ssdm name="store_ln30"/></StgValue>
</operation>
</state>

<state id="5" st_id="6">

<operation id="74" st_id="5" stage="1" lat="1">
<core>NULL</core>
<MemPortIdVec></MemPortIdVec>
<condition id="-1">
<or_exp><and_exp></and_exp></or_exp>
</condition>

<Node id="35" bw="32" op_0_bw="32" op_1_bw="64">
<![CDATA[
for.inc244:5 %Layer_Weights_addr = getelementptr i32 %Layer_Weights, i64 %sext_ln75_cast

]]></Node>
<StgValue><ssdm name="Layer_Weights_addr"/></StgValue>
</operation>

<operation id="75" st_id="5" stage="1" lat="1">
<core>m_axi</core>
<MemPortIdVec></MemPortIdVec>
<condition id="-1">
<or_exp><and_exp></and_exp></or_exp>
</condition>

<Node id="55" bw="32" op_0_bw="32" op_1_bw="32">
<![CDATA[
for.inc244:25 %Layer_Weights_addr_read = read i32 @_ssdm_op_Read.m_axi.p1i32, i32 %Layer_Weights_addr

]]></Node>
<StgValue><ssdm name="Layer_Weights_addr_read"/></StgValue>
</operation>

<operation id="76" st_id="5" stage="1" lat="2">
<core>RAM</core>
<MemPortIdVec></MemPortIdVec>
<condition id="-1">
<or_exp><and_exp></and_exp></or_exp>
</condition>

<Node id="63" bw="32" op_0_bw="11">
<![CDATA[
for.inc244:33 %Layer3_Neurons_CPU_load = load i11 %Layer3_Neurons_CPU_addr

]]></Node>
<StgValue><ssdm name="Layer3_Neurons_CPU_load"/></StgValue>
</operation>
</state>

<state id="6" st_id="7">

<operation id="77" st_id="6" stage="1" lat="1">
<core>NULL</core>
<MemPortIdVec></MemPortIdVec>
<condition id="-1">
<or_exp><and_exp></and_exp></or_exp>
</condition>

<Node id="56" bw="32" op_0_bw="32">
<![CDATA[
for.inc244:26 %bitcast_ln79 = bitcast i32 %Layer_Weights_addr_read

]]></Node>
<StgValue><ssdm name="bitcast_ln79"/></StgValue>
</operation>

<operation id="78" st_id="6" stage="2" lat="2">
<core>FMul_maxdsp</core>
<MemPortIdVec></MemPortIdVec>
<condition id="-1">
<or_exp><and_exp></and_exp></or_exp>
</condition>

<Node id="64" bw="32" op_0_bw="32" op_1_bw="32">
<![CDATA[
for.inc244:34 %mul7 = fmul i32 %bitcast_ln79, i32 %Layer3_Neurons_CPU_load

]]></Node>
<StgValue><ssdm name="mul7"/></StgValue>
</operation>
</state>

<state id="7" st_id="8">

<operation id="79" st_id="7" stage="1" lat="2">
<core>FMul_maxdsp</core>
<MemPortIdVec></MemPortIdVec>
<condition id="-1">
<or_exp><and_exp></and_exp></or_exp>
</condition>

<Node id="64" bw="32" op_0_bw="32" op_1_bw="32">
<![CDATA[
for.inc244:34 %mul7 = fmul i32 %bitcast_ln79, i32 %Layer3_Neurons_CPU_load

]]></Node>
<StgValue><ssdm name="mul7"/></StgValue>
</operation>
</state>

<state id="8" st_id="9">

<operation id="80" st_id="8" stage="1" lat="1">
<core>NULL</core>
<MemPortIdVec></MemPortIdVec>
<condition id="-1">
<or_exp><and_exp></and_exp></or_exp>
</condition>

<Node id="30" bw="32" op_0_bw="32" op_1_bw="0">
<![CDATA[
for.inc244:0 %somme_1_load_1 = load i32 %somme_1

]]></Node>
<StgValue><ssdm name="somme_1_load_1"/></StgValue>
</operation>

<operation id="81" st_id="8" stage="4" lat="4">
<core>FAddSub_fulldsp</core>
<MemPortIdVec></MemPortIdVec>
<condition id="-1">
<or_exp><and_exp></and_exp></or_exp>
</condition>

<Node id="65" bw="32" op_0_bw="32" op_1_bw="32">
<![CDATA[
for.inc244:35 %somme_2 = fadd i32 %somme_1_load_1, i32 %mul7

]]></Node>
<StgValue><ssdm name="somme_2"/></StgValue>
</operation>

<operation id="90" st_id="8" stage="1" lat="1">
<core>NULL</core>
<MemPortIdVec></MemPortIdVec>
<condition id="-1">
<or_exp><and_exp><literal name="icmp_ln75" val="1"/>
</and_exp></or_exp>
</condition>

<Node id="77" bw="32" op_0_bw="32" op_1_bw="0">
<![CDATA[
for.inc250.exitStub:0 %somme_1_load = load i32 %somme_1

]]></Node>
<StgValue><ssdm name="somme_1_load"/></StgValue>
</operation>

<operation id="91" st_id="8" stage="1" lat="1">
<core>NULL</core>
<MemPortIdVec></MemPortIdVec>
<condition id="-1">
<or_exp><and_exp><literal name="icmp_ln75" val="1"/>
</and_exp></or_exp>
</condition>

<Node id="78" bw="0" op_0_bw="0" op_1_bw="32" op_2_bw="32">
<![CDATA[
for.inc250.exitStub:1 %write_ln0 = write void @_ssdm_op_Write.ap_auto.floatP0A, i32 %somme_61_out, i32 %somme_1_load

]]></Node>
<StgValue><ssdm name="write_ln0"/></StgValue>
</operation>

<operation id="92" st_id="8" stage="1" lat="1">
<core>NULL</core>
<MemPortIdVec></MemPortIdVec>
<condition id="-1">
<or_exp><and_exp><literal name="icmp_ln75" val="1"/>
</and_exp></or_exp>
</condition>

<Node id="79" bw="0">
<![CDATA[
for.inc250.exitStub:2 %ret_ln0 = ret

]]></Node>
<StgValue><ssdm name="ret_ln0"/></StgValue>
</operation>
</state>

<state id="9" st_id="10">

<operation id="82" st_id="9" stage="3" lat="4">
<core>FAddSub_fulldsp</core>
<MemPortIdVec></MemPortIdVec>
<condition id="-1">
<or_exp><and_exp></and_exp></or_exp>
</condition>

<Node id="65" bw="32" op_0_bw="32" op_1_bw="32">
<![CDATA[
for.inc244:35 %somme_2 = fadd i32 %somme_1_load_1, i32 %mul7

]]></Node>
<StgValue><ssdm name="somme_2"/></StgValue>
</operation>
</state>

<state id="10" st_id="11">

<operation id="83" st_id="10" stage="2" lat="4">
<core>FAddSub_fulldsp</core>
<MemPortIdVec></MemPortIdVec>
<condition id="-1">
<or_exp><and_exp></and_exp></or_exp>
</condition>

<Node id="65" bw="32" op_0_bw="32" op_1_bw="32">
<![CDATA[
for.inc244:35 %somme_2 = fadd i32 %somme_1_load_1, i32 %mul7

]]></Node>
<StgValue><ssdm name="somme_2"/></StgValue>
</operation>
</state>

<state id="11" st_id="12">

<operation id="84" st_id="11" stage="1" lat="1">
<core>NULL</core>
<MemPortIdVec></MemPortIdVec>
<condition id="-1">
<or_exp><and_exp></and_exp></or_exp>
</condition>

<Node id="36" bw="0" op_0_bw="0" op_1_bw="0">
<![CDATA[
for.inc244:6 %specloopname_ln0 = specloopname void @_ssdm_op_SpecLoopName, void @col_loop2_kernelRow_Loop2_kernelCol_loop2_str

]]></Node>
<StgValue><ssdm name="specloopname_ln0"/></StgValue>
</operation>

<operation id="85" st_id="11" stage="1" lat="1">
<core>NULL</core>
<MemPortIdVec></MemPortIdVec>
<condition id="-1">
<or_exp><and_exp></and_exp></or_exp>
</condition>

<Node id="37" bw="0" op_0_bw="0" op_1_bw="64" op_2_bw="64" op_3_bw="64">
<![CDATA[
for.inc244:7 %speclooptripcount_ln0 = speclooptripcount void @_ssdm_op_SpecLoopTripCount, i64 1250, i64 1250, i64 1250

]]></Node>
<StgValue><ssdm name="speclooptripcount_ln0"/></StgValue>
</operation>

<operation id="86" st_id="11" stage="1" lat="1">
<core>NULL</core>
<MemPortIdVec></MemPortIdVec>
<condition id="-1">
<or_exp><and_exp></and_exp></or_exp>
</condition>

<Node id="54" bw="0" op_0_bw="0" op_1_bw="32" op_2_bw="32" op_3_bw="32" op_4_bw="32" op_5_bw="0">
<![CDATA[
for.inc244:24 %specpipeline_ln78 = specpipeline void @_ssdm_op_SpecPipeline, i32 3, i32 0, i32 0, i32 0, void @empty_0

]]></Node>
<StgValue><ssdm name="specpipeline_ln78"/></StgValue>
</operation>

<operation id="87" st_id="11" stage="1" lat="4">
<core>FAddSub_fulldsp</core>
<MemPortIdVec></MemPortIdVec>
<condition id="-1">
<or_exp><and_exp></and_exp></or_exp>
</condition>

<Node id="65" bw="32" op_0_bw="32" op_1_bw="32">
<![CDATA[
for.inc244:35 %somme_2 = fadd i32 %somme_1_load_1, i32 %mul7

]]></Node>
<StgValue><ssdm name="somme_2"/></StgValue>
</operation>

<operation id="88" st_id="11" stage="1" lat="1">
<core>NULL</core>
<MemPortIdVec></MemPortIdVec>
<condition id="-1">
<or_exp><and_exp></and_exp></or_exp>
</condition>

<Node id="74" bw="0" op_0_bw="32" op_1_bw="32" op_2_bw="0" op_3_bw="0">
<![CDATA[
for.inc244:44 %store_ln29 = store i32 %somme_2, i32 %somme_1

]]></Node>
<StgValue><ssdm name="store_ln29"/></StgValue>
</operation>

<operation id="89" st_id="11" stage="1" lat="1">
<core>NULL</core>
<MemPortIdVec></MemPortIdVec>
<condition id="-1">
<or_exp><and_exp></and_exp></or_exp>
</condition>

<Node id="75" bw="0" op_0_bw="0">
<![CDATA[
for.inc244:45 %br_ln77 = br void %for.inc238

]]></Node>
<StgValue><ssdm name="br_ln77"/></StgValue>
</operation>
</state>
</state_list>


<ports>
</ports>


<dataflows>
</dataflows>


</stg>
