{
  "Top": "calculateLayer2",
  "RtlTop": "calculateLayer2",
  "RtlPrefix": "",
  "RtlSubPrefix": "calculateLayer2_",
  "SourceLanguage": "cpp",
  "HostMachineBits": "64",
  "FunctionProtocol": "ap_ctrl_hs",
  "ResetStyle": "control",
  "Target": {
    "Family": "zynq",
    "Device": "xc7z020",
    "Package": "-clg484",
    "Speed": "-1",
    "Triple": "fpga64-xilinx-none"
  },
  "Args": {
    "Layer1_Neurons_CPU": {
      "index": "0",
      "direction": "inout",
      "srcType": "float*",
      "srcSize": "32",
      "hwRefs": [
        {
          "type": "interface",
          "interface": "m_axi_gmem",
          "name": "",
          "usage": "data",
          "direction": "inout"
        },
        {
          "type": "register",
          "interface": "s_axi_CTRL_bus",
          "name": "Layer1_Neurons_CPU_1",
          "usage": "address",
          "direction": "in"
        },
        {
          "type": "register",
          "interface": "s_axi_CTRL_bus",
          "name": "Layer1_Neurons_CPU_2",
          "usage": "address",
          "direction": "in"
        }
      ]
    },
    "Layer1_Weights_CPU": {
      "index": "1",
      "direction": "in",
      "srcType": "float*",
      "srcSize": "32",
      "hwRefs": [
        {
          "type": "interface",
          "interface": "Layer1_Weights_CPU_PORTA",
          "name": "",
          "usage": "data",
          "direction": "in"
        },
        {
          "type": "interface",
          "interface": "Layer1_Weights_CPU_PORTB",
          "name": "",
          "usage": "data",
          "direction": "in"
        }
      ]
    },
    "Layer2_Neurons_CPU": {
      "index": "2",
      "direction": "inout",
      "srcType": "float*",
      "srcSize": "32",
      "hwRefs": [
        {
          "type": "interface",
          "interface": "m_axi_gmem",
          "name": "",
          "usage": "data",
          "direction": "inout"
        },
        {
          "type": "register",
          "interface": "s_axi_CTRL_bus",
          "name": "Layer2_Neurons_CPU_1",
          "usage": "address",
          "direction": "in"
        },
        {
          "type": "register",
          "interface": "s_axi_CTRL_bus",
          "name": "Layer2_Neurons_CPU_2",
          "usage": "address",
          "direction": "in"
        }
      ]
    }
  },
  "HlsSolution": {
    "FlowTarget": "vivado",
    "ConfigTcl": [
      "config_cosim -tool=xsim",
      "config_cosim -trace_level=port",
      "config_export -format=ip_catalog",
      "config_export -rtl=verilog"
    ],
    "DirectiveTcl": [
      "set_directive_top calculateLayer2 -name calculateLayer2",
      "set_directive_top calculateLayer2 -name calculateLayer2"
    ],
    "ProfileOption": "0",
    "ProfileType": "none",
    "KernelName": "calculateLayer2"
  },
  "ClockInfo": {
    "ClockName": "ap_clk",
    "ClockPeriod": "10",
    "Uncertainty": "2.7",
    "IsCombinational": "0",
    "II": "28542",
    "Latency": "28541"
  },
  "Xdc": {"OocClocks": ["create_clock -name ap_clk -period 10.000 [get_ports ap_clk]"]},
  "Ipx": {
    "Vendor": "xilinx.com",
    "Library": "hls",
    "Name": "calculateLayer2",
    "Version": "1.0",
    "DisplayName": "Calculatelayer2",
    "Revision": "2113930212",
    "Description": "An IP generated by Vitis HLS",
    "Taxonomy": "\/VITIS_HLS_IP",
    "AutoFamilySupport": "",
    "ZipFile": "xilinx_com_hls_calculateLayer2_1_0.zip"
  },
  "Files": {
    "CSource": [
      "..\/..\/calculateLayer2.cpp",
      "..\/..\/sigmoid.cpp"
    ],
    "Vhdl": [
      "impl\/vhdl\/calculateLayer2_CTRL_bus_s_axi.vhd",
      "impl\/vhdl\/calculateLayer2_fadd_32ns_32ns_32_5_full_dsp_1.vhd",
      "impl\/vhdl\/calculateLayer2_fcmp_32ns_32ns_1_2_no_dsp_1.vhd",
      "impl\/vhdl\/calculateLayer2_fdiv_32ns_32ns_32_16_no_dsp_1.vhd",
      "impl\/vhdl\/calculateLayer2_fmul_32ns_32ns_32_4_max_dsp_1.vhd",
      "impl\/vhdl\/calculateLayer2_fmul_32ns_32ns_32_4_max_dsp_1_x.vhd",
      "impl\/vhdl\/calculateLayer2_gmem_m_axi.vhd",
      "impl\/vhdl\/calculateLayer2_mul_3ns_6ns_8_1_1.vhd",
      "impl\/vhdl\/calculateLayer2_mul_4ns_7ns_10_1_1.vhd",
      "impl\/vhdl\/calculateLayer2_SIGMOID.vhd",
      "impl\/vhdl\/calculateLayer2_SIGMOID_sigmoidLUT_1_ROM_AUTO_1R.vhd",
      "impl\/vhdl\/calculateLayer2.vhd"
    ],
    "Verilog": [
      "impl\/verilog\/calculateLayer2_CTRL_bus_s_axi.v",
      "impl\/verilog\/calculateLayer2_fadd_32ns_32ns_32_5_full_dsp_1.v",
      "impl\/verilog\/calculateLayer2_fcmp_32ns_32ns_1_2_no_dsp_1.v",
      "impl\/verilog\/calculateLayer2_fdiv_32ns_32ns_32_16_no_dsp_1.v",
      "impl\/verilog\/calculateLayer2_fmul_32ns_32ns_32_4_max_dsp_1.v",
      "impl\/verilog\/calculateLayer2_fmul_32ns_32ns_32_4_max_dsp_1_x.v",
      "impl\/verilog\/calculateLayer2_gmem_m_axi.v",
      "impl\/verilog\/calculateLayer2_mul_3ns_6ns_8_1_1.v",
      "impl\/verilog\/calculateLayer2_mul_4ns_7ns_10_1_1.v",
      "impl\/verilog\/calculateLayer2_SIGMOID.v",
      "impl\/verilog\/calculateLayer2_SIGMOID_sigmoidLUT_1_ROM_AUTO_1R.dat",
      "impl\/verilog\/calculateLayer2_SIGMOID_sigmoidLUT_1_ROM_AUTO_1R.v",
      "impl\/verilog\/calculateLayer2.v"
    ],
    "SwDriver": [
      "impl\/misc\/drivers\/calculateLayer2_v1_0\/data\/calculateLayer2.mdd",
      "impl\/misc\/drivers\/calculateLayer2_v1_0\/data\/calculateLayer2.tcl",
      "impl\/misc\/drivers\/calculateLayer2_v1_0\/data\/calculateLayer2.yaml",
      "impl\/misc\/drivers\/calculateLayer2_v1_0\/src\/CMakeLists.txt",
      "impl\/misc\/drivers\/calculateLayer2_v1_0\/src\/Makefile",
      "impl\/misc\/drivers\/calculateLayer2_v1_0\/src\/xcalculatelayer2.c",
      "impl\/misc\/drivers\/calculateLayer2_v1_0\/src\/xcalculatelayer2.h",
      "impl\/misc\/drivers\/calculateLayer2_v1_0\/src\/xcalculatelayer2_hw.h",
      "impl\/misc\/drivers\/calculateLayer2_v1_0\/src\/xcalculatelayer2_linux.c",
      "impl\/misc\/drivers\/calculateLayer2_v1_0\/src\/xcalculatelayer2_sinit.c"
    ],
    "IpMisc": ["impl\/misc\/logo.png"],
    "Subcore": [
      "impl\/misc\/calculateLayer2_fadd_32ns_32ns_32_5_full_dsp_1_ip.tcl",
      "impl\/misc\/calculateLayer2_fcmp_32ns_32ns_1_2_no_dsp_1_ip.tcl",
      "impl\/misc\/calculateLayer2_fdiv_32ns_32ns_32_16_no_dsp_1_ip.tcl",
      "impl\/misc\/calculateLayer2_fmul_32ns_32ns_32_4_max_dsp_1_ip.tcl",
      "impl\/misc\/calculateLayer2_fmul_32ns_32ns_32_4_max_dsp_1_x_ip.tcl"
    ],
    "CsynthXml": "syn\/report\/csynth.xml",
    "DebugDir": ".debug",
    "KernelXml": ".autopilot\/db\/kernel.internal.xml",
    "Xo": "",
    "XoHlsDir": "",
    "ProtoInst": [
      ".debug\/calculateLayer2.protoinst",
      ".debug\/calculateLayer4.protoinst"
    ]
  },
  "SubcoreInfo": {
    "HasXpmMemory": false,
    "HasClockedDsp": false,
    "Ip": [
      {
        "Name": "calculateLayer2_fadd_32ns_32ns_32_5_full_dsp_1_ip",
        "Vlnv": "xilinx.com:ip:floating_point:7.1",
        "Params": "CONFIG.a_precision_type Single CONFIG.a_tuser_width 1 CONFIG.add_sub_value Add CONFIG.b_tuser_width 1 CONFIG.c_a_exponent_width 8 CONFIG.c_a_fraction_width 24 CONFIG.c_compare_operation Programmable CONFIG.c_has_divide_by_zero false CONFIG.c_has_invalid_op false CONFIG.c_has_overflow false CONFIG.c_has_underflow false CONFIG.c_latency 3 CONFIG.c_mult_usage Full_Usage CONFIG.c_optimization Speed_Optimized CONFIG.c_rate 1 CONFIG.c_result_exponent_width 8 CONFIG.c_result_fraction_width 24 CONFIG.component_name calculateLayer2_fadd_32ns_32ns_32_5_full_dsp_1_ip CONFIG.flow_control NonBlocking CONFIG.has_a_tlast false CONFIG.has_a_tuser false CONFIG.has_aclken true CONFIG.has_aresetn false CONFIG.has_b_tlast false CONFIG.has_b_tuser false CONFIG.has_operation_tlast false CONFIG.has_operation_tuser false CONFIG.has_result_tready false CONFIG.maximum_latency false CONFIG.operation_tuser_width 1 CONFIG.operation_type Add_Subtract CONFIG.result_precision_type Single CONFIG.result_tlast_behv Null"
      },
      {
        "Name": "calculateLayer2_fcmp_32ns_32ns_1_2_no_dsp_1_ip",
        "Vlnv": "xilinx.com:ip:floating_point:7.1",
        "Params": "CONFIG.a_precision_type Single CONFIG.a_tuser_width 1 CONFIG.add_sub_value Both CONFIG.b_tuser_width 1 CONFIG.c_a_exponent_width 8 CONFIG.c_a_fraction_width 24 CONFIG.c_compare_operation Programmable CONFIG.c_has_divide_by_zero false CONFIG.c_has_invalid_op false CONFIG.c_has_overflow false CONFIG.c_has_underflow false CONFIG.c_latency 0 CONFIG.c_mult_usage No_Usage CONFIG.c_optimization Speed_Optimized CONFIG.c_rate 1 CONFIG.c_result_exponent_width 1 CONFIG.c_result_fraction_width 0 CONFIG.component_name calculateLayer2_fcmp_32ns_32ns_1_2_no_dsp_1_ip CONFIG.flow_control NonBlocking CONFIG.has_a_tlast false CONFIG.has_a_tuser false CONFIG.has_aclken false CONFIG.has_aresetn false CONFIG.has_b_tlast false CONFIG.has_b_tuser false CONFIG.has_operation_tlast false CONFIG.has_operation_tuser false CONFIG.has_result_tready false CONFIG.maximum_latency false CONFIG.operation_tuser_width 1 CONFIG.operation_type Compare CONFIG.result_precision_type Single CONFIG.result_tlast_behv Null"
      },
      {
        "Name": "calculateLayer2_fdiv_32ns_32ns_32_16_no_dsp_1_ip",
        "Vlnv": "xilinx.com:ip:floating_point:7.1",
        "Params": "CONFIG.a_precision_type Single CONFIG.a_tuser_width 1 CONFIG.add_sub_value Both CONFIG.b_tuser_width 1 CONFIG.c_a_exponent_width 8 CONFIG.c_a_fraction_width 24 CONFIG.c_compare_operation Programmable CONFIG.c_has_divide_by_zero false CONFIG.c_has_invalid_op false CONFIG.c_has_overflow false CONFIG.c_has_underflow false CONFIG.c_latency 14 CONFIG.c_mult_usage No_Usage CONFIG.c_optimization Speed_Optimized CONFIG.c_rate 1 CONFIG.c_result_exponent_width 8 CONFIG.c_result_fraction_width 24 CONFIG.component_name calculateLayer2_fdiv_32ns_32ns_32_16_no_dsp_1_ip CONFIG.flow_control NonBlocking CONFIG.has_a_tlast false CONFIG.has_a_tuser false CONFIG.has_aclken true CONFIG.has_aresetn false CONFIG.has_b_tlast false CONFIG.has_b_tuser false CONFIG.has_operation_tlast false CONFIG.has_operation_tuser false CONFIG.has_result_tready false CONFIG.maximum_latency false CONFIG.operation_tuser_width 1 CONFIG.operation_type Divide CONFIG.result_precision_type Single CONFIG.result_tlast_behv Null"
      },
      {
        "Name": "calculateLayer2_fmul_32ns_32ns_32_4_max_dsp_1_ip",
        "Vlnv": "xilinx.com:ip:floating_point:7.1",
        "Params": "CONFIG.a_precision_type Single CONFIG.a_tuser_width 1 CONFIG.add_sub_value Both CONFIG.b_tuser_width 1 CONFIG.c_a_exponent_width 8 CONFIG.c_a_fraction_width 24 CONFIG.c_compare_operation Programmable CONFIG.c_has_divide_by_zero false CONFIG.c_has_invalid_op false CONFIG.c_has_overflow false CONFIG.c_has_underflow false CONFIG.c_latency 2 CONFIG.c_mult_usage Max_Usage CONFIG.c_optimization Speed_Optimized CONFIG.c_rate 1 CONFIG.c_result_exponent_width 8 CONFIG.c_result_fraction_width 24 CONFIG.component_name calculateLayer2_fmul_32ns_32ns_32_4_max_dsp_1_ip CONFIG.flow_control NonBlocking CONFIG.has_a_tlast false CONFIG.has_a_tuser false CONFIG.has_aclken true CONFIG.has_aresetn false CONFIG.has_b_tlast false CONFIG.has_b_tuser false CONFIG.has_operation_tlast false CONFIG.has_operation_tuser false CONFIG.has_result_tready false CONFIG.maximum_latency false CONFIG.operation_tuser_width 1 CONFIG.operation_type Multiply CONFIG.result_precision_type Single CONFIG.result_tlast_behv Null"
      },
      {
        "Name": "calculateLayer2_fmul_32ns_32ns_32_4_max_dsp_1_x_ip",
        "Vlnv": "xilinx.com:ip:floating_point:7.1",
        "Params": "CONFIG.a_precision_type Single CONFIG.a_tuser_width 1 CONFIG.add_sub_value Both CONFIG.b_tuser_width 1 CONFIG.c_a_exponent_width 8 CONFIG.c_a_fraction_width 24 CONFIG.c_compare_operation Programmable CONFIG.c_has_divide_by_zero false CONFIG.c_has_invalid_op false CONFIG.c_has_overflow false CONFIG.c_has_underflow false CONFIG.c_latency 2 CONFIG.c_mult_usage Max_Usage CONFIG.c_optimization Speed_Optimized CONFIG.c_rate 1 CONFIG.c_result_exponent_width 8 CONFIG.c_result_fraction_width 24 CONFIG.component_name calculateLayer2_fmul_32ns_32ns_32_4_max_dsp_1_x_ip CONFIG.flow_control NonBlocking CONFIG.has_a_tlast false CONFIG.has_a_tuser false CONFIG.has_aclken true CONFIG.has_aresetn false CONFIG.has_b_tlast false CONFIG.has_b_tuser false CONFIG.has_operation_tlast false CONFIG.has_operation_tuser false CONFIG.has_result_tready false CONFIG.maximum_latency false CONFIG.operation_tuser_width 1 CONFIG.operation_type Multiply CONFIG.result_precision_type Single CONFIG.result_tlast_behv Null"
      }
    ]
  },
  "Interfaces": {
    "s_axi_CTRL_bus": {
      "type": "axi4lite",
      "busTypeName": "aximm",
      "mode": "slave",
      "dataWidth": "32",
      "addrWidth": "6",
      "portPrefix": "s_axi_CTRL_bus_",
      "paramPrefix": "C_S_AXI_CTRL_BUS_",
      "ports": [
        "s_axi_CTRL_bus_ARADDR",
        "s_axi_CTRL_bus_ARREADY",
        "s_axi_CTRL_bus_ARVALID",
        "s_axi_CTRL_bus_AWADDR",
        "s_axi_CTRL_bus_AWREADY",
        "s_axi_CTRL_bus_AWVALID",
        "s_axi_CTRL_bus_BREADY",
        "s_axi_CTRL_bus_BRESP",
        "s_axi_CTRL_bus_BVALID",
        "s_axi_CTRL_bus_RDATA",
        "s_axi_CTRL_bus_RREADY",
        "s_axi_CTRL_bus_RRESP",
        "s_axi_CTRL_bus_RVALID",
        "s_axi_CTRL_bus_WDATA",
        "s_axi_CTRL_bus_WREADY",
        "s_axi_CTRL_bus_WSTRB",
        "s_axi_CTRL_bus_WVALID"
      ],
      "registers": [
        {
          "offset": "0x00",
          "name": "CTRL",
          "access": "RW",
          "description": "Control signals",
          "range": "32",
          "fields": [
            {
              "offset": "0",
              "width": "1",
              "name": "AP_START",
              "access": "RW",
              "description": "Control signal Register for 'ap_start'."
            },
            {
              "offset": "1",
              "width": "1",
              "name": "AP_DONE",
              "access": "R",
              "description": "Control signal Register for 'ap_done'."
            },
            {
              "offset": "2",
              "width": "1",
              "name": "AP_IDLE",
              "access": "R",
              "description": "Control signal Register for 'ap_idle'."
            },
            {
              "offset": "3",
              "width": "1",
              "name": "AP_READY",
              "access": "R",
              "description": "Control signal Register for 'ap_ready'."
            },
            {
              "offset": "4",
              "width": "3",
              "name": "RESERVED_1",
              "access": "R",
              "description": "Reserved.  0s on read."
            },
            {
              "offset": "7",
              "width": "1",
              "name": "AUTO_RESTART",
              "access": "RW",
              "description": "Control signal Register for 'auto_restart'."
            },
            {
              "offset": "8",
              "width": "1",
              "name": "RESERVED_2",
              "access": "R",
              "description": "Reserved.  0s on read."
            },
            {
              "offset": "9",
              "width": "1",
              "name": "INTERRUPT",
              "access": "R",
              "description": "Control signal Register for 'interrupt'."
            },
            {
              "offset": "10",
              "width": "22",
              "name": "RESERVED_3",
              "access": "R",
              "description": "Reserved.  0s on read."
            }
          ]
        },
        {
          "offset": "0x04",
          "name": "GIER",
          "access": "RW",
          "description": "Global Interrupt Enable Register",
          "range": "32",
          "fields": [
            {
              "offset": "0",
              "width": "1",
              "name": "Enable",
              "access": "RW",
              "description": "Master enable for the device interrupt output to the system interrupt controller: 0 = Disabled, 1 = Enabled"
            },
            {
              "offset": "1",
              "width": "31",
              "name": "RESERVED",
              "access": "R",
              "description": "Reserved.  0s on read."
            }
          ]
        },
        {
          "offset": "0x08",
          "name": "IP_IER",
          "access": "RW",
          "description": "IP Interrupt Enable Register",
          "range": "32",
          "fields": [
            {
              "offset": "0",
              "width": "1",
              "name": "CHAN0_INT_EN",
              "access": "RW",
              "description": "Enable Channel 0 (ap_done) Interrupt.  0 = Disabled, 1 = Enabled."
            },
            {
              "offset": "1",
              "width": "1",
              "name": "CHAN1_INT_EN",
              "access": "RW",
              "description": "Enable Channel 1 (ap_ready) Interrupt.  0 = Disabled, 1 = Enabled."
            },
            {
              "offset": "2",
              "width": "30",
              "name": "RESERVED_0",
              "access": "R",
              "description": "Reserved.  0s on read."
            }
          ]
        },
        {
          "offset": "0x0c",
          "name": "IP_ISR",
          "access": "RW",
          "description": "IP Interrupt Status Register",
          "range": "32",
          "fields": [
            {
              "offset": "0",
              "width": "1",
              "name": "CHAN0_INT_ST",
              "access": "RTOW",
              "description": "Channel 0 (ap_done) Interrupt Status. 0 = No Channel 0 interrupt, 1 = Channel 0 interrupt."
            },
            {
              "offset": "1",
              "width": "1",
              "name": "CHAN1_INT_ST",
              "access": "RTOW",
              "description": "Channel 1 (ap_ready) Interrupt Status. 0 = No Channel 1 interrupt, 1 = Channel 1 interrupt."
            },
            {
              "offset": "2",
              "width": "30",
              "name": "RESERVED_0",
              "access": "R",
              "description": "Reserved.  0s on read."
            }
          ]
        },
        {
          "offset": "0x10",
          "name": "Layer1_Neurons_CPU_1",
          "access": "W",
          "description": "Data signal of Layer1_Neurons_CPU",
          "range": "32",
          "fields": [{
              "offset": "0",
              "width": "32",
              "name": "Layer1_Neurons_CPU",
              "access": "W",
              "description": "Bit 31 to 0 of Layer1_Neurons_CPU"
            }]
        },
        {
          "offset": "0x14",
          "name": "Layer1_Neurons_CPU_2",
          "access": "W",
          "description": "Data signal of Layer1_Neurons_CPU",
          "range": "32",
          "fields": [{
              "offset": "0",
              "width": "32",
              "name": "Layer1_Neurons_CPU",
              "access": "W",
              "description": "Bit 63 to 32 of Layer1_Neurons_CPU"
            }]
        },
        {
          "offset": "0x1c",
          "name": "Layer2_Neurons_CPU_1",
          "access": "W",
          "description": "Data signal of Layer2_Neurons_CPU",
          "range": "32",
          "fields": [{
              "offset": "0",
              "width": "32",
              "name": "Layer2_Neurons_CPU",
              "access": "W",
              "description": "Bit 31 to 0 of Layer2_Neurons_CPU"
            }]
        },
        {
          "offset": "0x20",
          "name": "Layer2_Neurons_CPU_2",
          "access": "W",
          "description": "Data signal of Layer2_Neurons_CPU",
          "range": "32",
          "fields": [{
              "offset": "0",
              "width": "32",
              "name": "Layer2_Neurons_CPU",
              "access": "W",
              "description": "Bit 63 to 32 of Layer2_Neurons_CPU"
            }]
        }
      ],
      "constraints": [
        {
          "constraint_type": "pragma interface",
          "mode": "s_axilite",
          "register_option": "0",
          "offset": "16",
          "argName": "Layer1_Neurons_CPU"
        },
        {
          "constraint_type": "pragma interface",
          "mode": "s_axilite",
          "register_option": "0",
          "offset": "28",
          "argName": "Layer2_Neurons_CPU"
        }
      ]
    },
    "ap_clk": {
      "type": "clock",
      "busTypeName": "clock",
      "mode": "slave",
      "busParams": {
        "ASSOCIATED_BUSIF": "s_axi_CTRL_bus:m_axi_gmem",
        "ASSOCIATED_RESET": "ap_rst_n"
      },
      "portMap": {"ap_clk": "CLK"},
      "ports": ["ap_clk"]
    },
    "ap_rst_n": {
      "type": "reset",
      "busTypeName": "reset",
      "mode": "slave",
      "busParams": {"POLARITY": "ACTIVE_LOW"},
      "portMap": {"ap_rst_n": "RST"},
      "ports": ["ap_rst_n"]
    },
    "interrupt": {
      "type": "interrupt",
      "busTypeName": "interrupt",
      "mode": "master",
      "dataWidth": "1",
      "busParams": {"SENSITIVITY": "LEVEL_HIGH"},
      "portMap": {"interrupt": "INTERRUPT"},
      "ports": ["interrupt"]
    },
    "m_axi_gmem": {
      "type": "axi4full",
      "busTypeName": "aximm",
      "mode": "master",
      "dataWidth": "32",
      "addrWidth": "64",
      "portPrefix": "m_axi_gmem_",
      "paramPrefix": "C_M_AXI_GMEM_",
      "preferredUsageValue": "MEMORY",
      "busParams": {
        "NUM_READ_OUTSTANDING": "16",
        "NUM_WRITE_OUTSTANDING": "16",
        "MAX_READ_BURST_LENGTH": "16",
        "MAX_WRITE_BURST_LENGTH": "16",
        "MAX_BURST_LENGTH": "256",
        "PROTOCOL": "AXI4",
        "READ_WRITE_MODE": "READ_WRITE",
        "HAS_BURST": "0",
        "SUPPORTS_NARROW_BURST": "0"
      },
      "ports": [
        "m_axi_gmem_ARADDR",
        "m_axi_gmem_ARBURST",
        "m_axi_gmem_ARCACHE",
        "m_axi_gmem_ARID",
        "m_axi_gmem_ARLEN",
        "m_axi_gmem_ARLOCK",
        "m_axi_gmem_ARPROT",
        "m_axi_gmem_ARQOS",
        "m_axi_gmem_ARREADY",
        "m_axi_gmem_ARREGION",
        "m_axi_gmem_ARSIZE",
        "m_axi_gmem_ARUSER",
        "m_axi_gmem_ARVALID",
        "m_axi_gmem_AWADDR",
        "m_axi_gmem_AWBURST",
        "m_axi_gmem_AWCACHE",
        "m_axi_gmem_AWID",
        "m_axi_gmem_AWLEN",
        "m_axi_gmem_AWLOCK",
        "m_axi_gmem_AWPROT",
        "m_axi_gmem_AWQOS",
        "m_axi_gmem_AWREADY",
        "m_axi_gmem_AWREGION",
        "m_axi_gmem_AWSIZE",
        "m_axi_gmem_AWUSER",
        "m_axi_gmem_AWVALID",
        "m_axi_gmem_BID",
        "m_axi_gmem_BREADY",
        "m_axi_gmem_BRESP",
        "m_axi_gmem_BUSER",
        "m_axi_gmem_BVALID",
        "m_axi_gmem_RDATA",
        "m_axi_gmem_RID",
        "m_axi_gmem_RLAST",
        "m_axi_gmem_RREADY",
        "m_axi_gmem_RRESP",
        "m_axi_gmem_RUSER",
        "m_axi_gmem_RVALID",
        "m_axi_gmem_WDATA",
        "m_axi_gmem_WID",
        "m_axi_gmem_WLAST",
        "m_axi_gmem_WREADY",
        "m_axi_gmem_WSTRB",
        "m_axi_gmem_WUSER",
        "m_axi_gmem_WVALID"
      ],
      "constraints": [
        {
          "constraint_type": "pragma interface",
          "mode": "m_axi",
          "register_option": "0",
          "offset": "slave",
          "latency": "0",
          "num_read_outstanding": "16",
          "num_write_outstanding": "16",
          "max_read_burst_length": "16",
          "max_write_burst_length": "16",
          "max_widen_bitwidth": "0",
          "argName": "Layer1_Neurons_CPU"
        },
        {
          "constraint_type": "bitwidth",
          "orig_bitwidth": "32",
          "final_bitwidth": "32",
          "argName": "Layer1_Neurons_CPU"
        },
        {
          "constraint_type": "pragma interface",
          "mode": "m_axi",
          "register_option": "0",
          "offset": "slave",
          "latency": "0",
          "num_read_outstanding": "16",
          "num_write_outstanding": "16",
          "max_read_burst_length": "16",
          "max_write_burst_length": "16",
          "max_widen_bitwidth": "0",
          "argName": "Layer2_Neurons_CPU"
        },
        {
          "constraint_type": "bitwidth",
          "orig_bitwidth": "32",
          "final_bitwidth": "32",
          "argName": "Layer2_Neurons_CPU"
        }
      ]
    },
    "Layer1_Weights_CPU_PORTA": {
      "type": "bram",
      "busTypeName": "bram",
      "mode": "master",
      "dataWidth": "32",
      "addrWidth": "32",
      "portPrefix": "Layer1_Weights_CPU_",
      "busParams": {
        "MASTER_TYPE": "BRAM_CTRL",
        "MEM_WIDTH": "32",
        "MEM_SIZE": "4"
      },
      "portMap": {
        "Layer1_Weights_CPU_Addr_A": "ADDR",
        "Layer1_Weights_CPU_EN_A": "EN",
        "Layer1_Weights_CPU_WEN_A": "WE",
        "Layer1_Weights_CPU_Din_A": "DIN",
        "Layer1_Weights_CPU_Dout_A": "DOUT",
        "Layer1_Weights_CPU_Clk_A": "CLK",
        "Layer1_Weights_CPU_Rst_A": "RST"
      },
      "ports": [
        "Layer1_Weights_CPU_Addr_A",
        "Layer1_Weights_CPU_Clk_A",
        "Layer1_Weights_CPU_Din_A",
        "Layer1_Weights_CPU_Dout_A",
        "Layer1_Weights_CPU_EN_A",
        "Layer1_Weights_CPU_Rst_A",
        "Layer1_Weights_CPU_WEN_A"
      ],
      "constraints": [{
          "constraint_type": "pragma interface",
          "mode": "bram",
          "register_option": "0",
          "argName": "Layer1_Weights_CPU"
        }]
    },
    "Layer1_Weights_CPU_PORTB": {
      "type": "bram",
      "busTypeName": "bram",
      "mode": "master",
      "dataWidth": "32",
      "addrWidth": "32",
      "portPrefix": "Layer1_Weights_CPU_",
      "busParams": {
        "MASTER_TYPE": "BRAM_CTRL",
        "MEM_WIDTH": "32",
        "MEM_SIZE": "4"
      },
      "portMap": {
        "Layer1_Weights_CPU_Addr_B": "ADDR",
        "Layer1_Weights_CPU_EN_B": "EN",
        "Layer1_Weights_CPU_WEN_B": "WE",
        "Layer1_Weights_CPU_Din_B": "DIN",
        "Layer1_Weights_CPU_Dout_B": "DOUT",
        "Layer1_Weights_CPU_Clk_B": "CLK",
        "Layer1_Weights_CPU_Rst_B": "RST"
      },
      "ports": [
        "Layer1_Weights_CPU_Addr_B",
        "Layer1_Weights_CPU_Clk_B",
        "Layer1_Weights_CPU_Din_B",
        "Layer1_Weights_CPU_Dout_B",
        "Layer1_Weights_CPU_EN_B",
        "Layer1_Weights_CPU_Rst_B",
        "Layer1_Weights_CPU_WEN_B"
      ],
      "constraints": [{
          "constraint_type": "pragma interface",
          "mode": "bram",
          "register_option": "0",
          "argName": "Layer1_Weights_CPU"
        }]
    }
  },
  "RtlPorts": {
    "s_axi_CTRL_bus_AWVALID": {
      "dir": "in",
      "width": "1"
    },
    "s_axi_CTRL_bus_AWREADY": {
      "dir": "out",
      "width": "1"
    },
    "s_axi_CTRL_bus_AWADDR": {
      "dir": "in",
      "width": "6"
    },
    "s_axi_CTRL_bus_WVALID": {
      "dir": "in",
      "width": "1"
    },
    "s_axi_CTRL_bus_WREADY": {
      "dir": "out",
      "width": "1"
    },
    "s_axi_CTRL_bus_WDATA": {
      "dir": "in",
      "width": "32"
    },
    "s_axi_CTRL_bus_WSTRB": {
      "dir": "in",
      "width": "4"
    },
    "s_axi_CTRL_bus_ARVALID": {
      "dir": "in",
      "width": "1"
    },
    "s_axi_CTRL_bus_ARREADY": {
      "dir": "out",
      "width": "1"
    },
    "s_axi_CTRL_bus_ARADDR": {
      "dir": "in",
      "width": "6"
    },
    "s_axi_CTRL_bus_RVALID": {
      "dir": "out",
      "width": "1"
    },
    "s_axi_CTRL_bus_RREADY": {
      "dir": "in",
      "width": "1"
    },
    "s_axi_CTRL_bus_RDATA": {
      "dir": "out",
      "width": "32"
    },
    "s_axi_CTRL_bus_RRESP": {
      "dir": "out",
      "width": "2"
    },
    "s_axi_CTRL_bus_BVALID": {
      "dir": "out",
      "width": "1"
    },
    "s_axi_CTRL_bus_BREADY": {
      "dir": "in",
      "width": "1"
    },
    "s_axi_CTRL_bus_BRESP": {
      "dir": "out",
      "width": "2"
    },
    "ap_clk": {
      "dir": "in",
      "width": "1"
    },
    "ap_rst_n": {
      "dir": "in",
      "width": "1"
    },
    "interrupt": {
      "dir": "out",
      "width": "1"
    },
    "m_axi_gmem_AWVALID": {
      "dir": "out",
      "width": "1"
    },
    "m_axi_gmem_AWREADY": {
      "dir": "in",
      "width": "1"
    },
    "m_axi_gmem_AWADDR": {
      "dir": "out",
      "width": "64"
    },
    "m_axi_gmem_AWID": {
      "dir": "out",
      "width": "1",
      "isVector": "true"
    },
    "m_axi_gmem_AWLEN": {
      "dir": "out",
      "width": "8"
    },
    "m_axi_gmem_AWSIZE": {
      "dir": "out",
      "width": "3"
    },
    "m_axi_gmem_AWBURST": {
      "dir": "out",
      "width": "2"
    },
    "m_axi_gmem_AWLOCK": {
      "dir": "out",
      "width": "2"
    },
    "m_axi_gmem_AWCACHE": {
      "dir": "out",
      "width": "4"
    },
    "m_axi_gmem_AWPROT": {
      "dir": "out",
      "width": "3"
    },
    "m_axi_gmem_AWQOS": {
      "dir": "out",
      "width": "4"
    },
    "m_axi_gmem_AWREGION": {
      "dir": "out",
      "width": "4"
    },
    "m_axi_gmem_AWUSER": {
      "dir": "out",
      "width": "1",
      "isVector": "true"
    },
    "m_axi_gmem_WVALID": {
      "dir": "out",
      "width": "1"
    },
    "m_axi_gmem_WREADY": {
      "dir": "in",
      "width": "1"
    },
    "m_axi_gmem_WDATA": {
      "dir": "out",
      "width": "32"
    },
    "m_axi_gmem_WSTRB": {
      "dir": "out",
      "width": "4"
    },
    "m_axi_gmem_WLAST": {
      "dir": "out",
      "width": "1"
    },
    "m_axi_gmem_WID": {
      "dir": "out",
      "width": "1",
      "isVector": "true"
    },
    "m_axi_gmem_WUSER": {
      "dir": "out",
      "width": "1",
      "isVector": "true"
    },
    "m_axi_gmem_ARVALID": {
      "dir": "out",
      "width": "1"
    },
    "m_axi_gmem_ARREADY": {
      "dir": "in",
      "width": "1"
    },
    "m_axi_gmem_ARADDR": {
      "dir": "out",
      "width": "64"
    },
    "m_axi_gmem_ARID": {
      "dir": "out",
      "width": "1",
      "isVector": "true"
    },
    "m_axi_gmem_ARLEN": {
      "dir": "out",
      "width": "8"
    },
    "m_axi_gmem_ARSIZE": {
      "dir": "out",
      "width": "3"
    },
    "m_axi_gmem_ARBURST": {
      "dir": "out",
      "width": "2"
    },
    "m_axi_gmem_ARLOCK": {
      "dir": "out",
      "width": "2"
    },
    "m_axi_gmem_ARCACHE": {
      "dir": "out",
      "width": "4"
    },
    "m_axi_gmem_ARPROT": {
      "dir": "out",
      "width": "3"
    },
    "m_axi_gmem_ARQOS": {
      "dir": "out",
      "width": "4"
    },
    "m_axi_gmem_ARREGION": {
      "dir": "out",
      "width": "4"
    },
    "m_axi_gmem_ARUSER": {
      "dir": "out",
      "width": "1",
      "isVector": "true"
    },
    "m_axi_gmem_RVALID": {
      "dir": "in",
      "width": "1"
    },
    "m_axi_gmem_RREADY": {
      "dir": "out",
      "width": "1"
    },
    "m_axi_gmem_RDATA": {
      "dir": "in",
      "width": "32"
    },
    "m_axi_gmem_RLAST": {
      "dir": "in",
      "width": "1"
    },
    "m_axi_gmem_RID": {
      "dir": "in",
      "width": "1",
      "isVector": "true"
    },
    "m_axi_gmem_RUSER": {
      "dir": "in",
      "width": "1",
      "isVector": "true"
    },
    "m_axi_gmem_RRESP": {
      "dir": "in",
      "width": "2"
    },
    "m_axi_gmem_BVALID": {
      "dir": "in",
      "width": "1"
    },
    "m_axi_gmem_BREADY": {
      "dir": "out",
      "width": "1"
    },
    "m_axi_gmem_BRESP": {
      "dir": "in",
      "width": "2"
    },
    "m_axi_gmem_BID": {
      "dir": "in",
      "width": "1",
      "isVector": "true"
    },
    "m_axi_gmem_BUSER": {
      "dir": "in",
      "width": "1",
      "isVector": "true"
    },
    "Layer1_Weights_CPU_Addr_A": {
      "dir": "out",
      "width": "32"
    },
    "Layer1_Weights_CPU_EN_A": {
      "dir": "out",
      "width": "1"
    },
    "Layer1_Weights_CPU_WEN_A": {
      "dir": "out",
      "width": "4"
    },
    "Layer1_Weights_CPU_Din_A": {
      "dir": "out",
      "width": "32"
    },
    "Layer1_Weights_CPU_Dout_A": {
      "dir": "in",
      "width": "32"
    },
    "Layer1_Weights_CPU_Clk_A": {
      "dir": "out",
      "width": "1"
    },
    "Layer1_Weights_CPU_Rst_A": {
      "dir": "out",
      "width": "1"
    },
    "Layer1_Weights_CPU_Addr_B": {
      "dir": "out",
      "width": "32"
    },
    "Layer1_Weights_CPU_EN_B": {
      "dir": "out",
      "width": "1"
    },
    "Layer1_Weights_CPU_WEN_B": {
      "dir": "out",
      "width": "4"
    },
    "Layer1_Weights_CPU_Din_B": {
      "dir": "out",
      "width": "32"
    },
    "Layer1_Weights_CPU_Dout_B": {
      "dir": "in",
      "width": "32"
    },
    "Layer1_Weights_CPU_Clk_B": {
      "dir": "out",
      "width": "1"
    },
    "Layer1_Weights_CPU_Rst_B": {
      "dir": "out",
      "width": "1"
    }
  },
  "ModuleInfo": {
    "Hierarchy": {
      "ModuleName": "calculateLayer2",
      "Instances": [{
          "ModuleName": "SIGMOID",
          "InstanceName": "grp_SIGMOID_fu_533"
        }]
    },
    "Info": {
      "SIGMOID": {
        "FunctionProtocol": "ap_ctrl_hs",
        "isTaskLevelControl": "0",
        "isPipelined": "1",
        "isCombinational": "0",
        "isOneStateSeq": "0"
      },
      "calculateLayer2": {
        "FunctionProtocol": "ap_ctrl_hs",
        "isTaskLevelControl": "0",
        "isPipelined": "0",
        "isCombinational": "0",
        "isOneStateSeq": "0"
      }
    },
    "Metrics": {
      "SIGMOID": {
        "Latency": {
          "LatencyBest": "28",
          "LatencyAvg": "28",
          "LatencyWorst": "28",
          "PipelineII": "4",
          "PipelineDepth": "29",
          "PipelineType": "yes"
        },
        "Timing": {
          "Target": "10.00",
          "Uncertainty": "2.70",
          "Estimate": "6.424"
        },
        "Area": {
          "BRAM_18K": "1",
          "AVAIL_BRAM": "280",
          "UTIL_BRAM": "~0",
          "DSP": "3",
          "AVAIL_DSP": "220",
          "UTIL_DSP": "1",
          "FF": "550",
          "AVAIL_FF": "106400",
          "UTIL_FF": "~0",
          "LUT": "1293",
          "AVAIL_LUT": "53200",
          "UTIL_LUT": "2",
          "URAM": "0",
          "AVAIL_URAM": "0",
          "UTIL_URAM": "0"
        }
      },
      "calculateLayer2": {
        "Latency": {
          "LatencyBest": "28541",
          "LatencyAvg": "28541",
          "LatencyWorst": "28541",
          "PipelineII": "28542",
          "PipelineDepth": "",
          "PipelineType": "no"
        },
        "Timing": {
          "Target": "10.00",
          "Uncertainty": "2.70",
          "Estimate": "8.280"
        },
        "Loops": [{
            "Name": "calculateLayer2_loop_OutputRow_Loop_OutputColumn_Loop",
            "TripCount": "1014",
            "Latency": "28539",
            "PipelineII": "28",
            "PipelineDepth": "176"
          }],
        "Area": {
          "BRAM_18K": "5",
          "AVAIL_BRAM": "280",
          "UTIL_BRAM": "1",
          "DSP": "8",
          "AVAIL_DSP": "220",
          "UTIL_DSP": "3",
          "FF": "5483",
          "AVAIL_FF": "106400",
          "UTIL_FF": "5",
          "LUT": "5441",
          "AVAIL_LUT": "53200",
          "UTIL_LUT": "10",
          "URAM": "0",
          "AVAIL_URAM": "0",
          "UTIL_URAM": "0"
        }
      }
    }
  },
  "GenerateBdFiles": "0",
  "GenData": {
    "DataVersion": "0.2",
    "Time": "2025-01-28 12:12:44 +0100",
    "ToolName": "vitis_hls",
    "ToolVersion": "2023.2"
  }
}
